.coveragerc
AUTHORS
ChangeLog
LICENSE
MANIFEST.in
Makefile
README.rst
pytest.ini
runtests
setup.cfg
setup.py
tox.ini
django_courier/__init__.py
django_courier/admin.py
django_courier/apps.py
django_courier/backends.py
django_courier/base.py
django_courier/models.py
django_courier/settings.py
django_courier/templates.py
django_courier.egg-info/PKG-INFO
django_courier.egg-info/SOURCES.txt
django_courier.egg-info/dependency_links.txt
django_courier.egg-info/not-zip-safe
django_courier.egg-info/pbr.json
django_courier.egg-info/requires.txt
django_courier.egg-info/top_level.txt
django_courier/extra/__init__.py
django_courier/extra/background.py
django_courier/management/__init__.py
django_courier/management/commands/__init__.py
django_courier/management/commands/make_notifications.py
django_courier/migrations/0001_initial.py
django_courier/migrations/0002_site_contacts.py
django_courier/migrations/0003_failed_messages.py
django_courier/migrations/0004_template_targets.py
django_courier/migrations/0005_contact_name.py
django_courier/migrations/0006_django2.py
django_courier/migrations/0007_migrations.py
django_courier/migrations/0008_notification_required.py
django_courier/migrations/0009_subjects.py
django_courier/migrations/0010_sender_recipient_models.py
django_courier/migrations/0011_notification_from_code.py
django_courier/migrations/0012_whitelist.py
django_courier/migrations/__init__.py
django_courier/static/django_courier/notification_fields.js
django_courier/static/django_courier/markitup/images.css
django_courier/static/django_courier/markitup/jquery.markitup.js
django_courier/static/django_courier/markitup/style.css
django_courier/static/django_courier/markitup/images/bold.png
django_courier/static/django_courier/markitup/images/code.png
django_courier/static/django_courier/markitup/images/handle.png
django_courier/static/django_courier/markitup/images/image.png
django_courier/static/django_courier/markitup/images/italic.png
django_courier/static/django_courier/markitup/images/link.png
django_courier/static/django_courier/markitup/images/list-bullet.png
django_courier/static/django_courier/markitup/images/list-numeric.png
django_courier/static/django_courier/markitup/images/menu.png
