Metadata-Version: 2.1
Name: django-courier
Version: 0.14.0
Summary: A notification app for Django
Home-page: https://gitlab.com/alantrick/django-courier
Author: Alan Trick
Author-email: me@alantrick.ca
License: LGPL
Project-URL: Bug Tracker, https://gitlab.com/alantrick/django-courier/issues
Project-URL: Documentation, http://djangocourier.readthedocs.io/en/latest/
Project-URL: Source Code, https://gitlab.com/alantrick/django-courier
Platform: UNKNOWN
Classifier: Development Status :: 3 - Alpha
Classifier: Environment :: Web Environment
Classifier: Framework :: Django
Classifier: Intended Audience :: Developers
Classifier: License :: OSI Approved :: GNU Lesser General Public License v3 or later (LGPLv3+)
Classifier: Operating System :: OS Independent
Classifier: Programming Language :: Python
Classifier: Programming Language :: Python :: 3.6
Classifier: Framework :: Django
Classifier: Framework :: Django :: 1.10
Classifier: Framework :: Django :: 1.11
Classifier: Framework :: Django :: 2.0
Classifier: Topic :: Utilities
Provides-Extra: markdown
Provides-Extra: docs
Provides-Extra: postmark
Provides-Extra: twilio
Provides-Extra: test
Provides-Extra: html
